{
	"configurations" : 
	[
		{
			"directories" : 
			[
				{
					"build" : ".",
					"jsonFile" : "directory-.-Debug-f5ebdc15457944623624.json",
					"minimumCMakeVersion" : 
					{
						"string" : "3.30"
					},
					"projectIndex" : 0,
					"source" : ".",
					"targetIndexes" : 
					[
						0
					]
				}
			],
			"name" : "Debug",
			"projects" : 
			[
				{
					"directoryIndexes" : 
					[
						0
					],
					"name" : "cpp_imageproc",
					"targetIndexes" : 
					[
						0
					]
				}
			],
			"targets" : 
			[
				{
					"directoryIndex" : 0,
					"id" : "cpp_imageproc::@6890427a1f51a3e7e1df",
					"jsonFile" : "target-cpp_imageproc-Debug-f70581e65f68d0dff3b7.json",
					"name" : "cpp_imageproc",
					"projectIndex" : 0
				}
			]
		}
	],
	"kind" : "codemodel",
	"paths" : 
	{
		"build" : "/Users/haorangan/CLionProjects/cpp-imageproc/cmake-build-debug",
		"source" : "/Users/haorangan/CLionProjects/cpp-imageproc"
	},
	"version" : 
	{
		"major" : 2,
		"minor" : 7
	}
}
